{
  "ok": true,
  "generatedAt": "2026-07-02T17:10:20.718Z",
  "bootId": "",
  "expectedFiles": [
    "runtime/full-section-matrix.json",
    "runtime/channel-target-matrix.json",
    "runtime/user-journey-matrix.json",
    "runtime/product-semantic-matrix.json",
    "runtime/tenant-channel-binding-matrix.json",
    "runtime/maximal-flow-matrix.json",
    "runtime/live-official-channel-resolution.json",
    "runtime/live-tenant-self-diagnostic-matrix.json",
    "runtime/tenant-section-matrix.json",
    "runtime/live-user-postgres-bindings.json",
    "runtime/process-events.json",
    "runtime/northflank-startup-log.json"
  ],
  "exports": [
    {
      "ok": true,
      "skipped": false,
      "configured": true,
      "branch": "runtime-status",
      "path": "runtime/channel-target-matrix.json",
      "attempts": 1,
      "durationMs": 9595
    },
    {
      "ok": true,
      "skipped": false,
      "configured": true,
      "branch": "runtime-status",
      "path": "runtime/full-section-matrix.json",
      "attempts": 1,
      "durationMs": 3499
    },
    {
      "ok": true,
      "skipped": false,
      "configured": true,
      "branch": "runtime-status",
      "path": "runtime/user-journey-matrix.json",
      "attempts": 1,
      "durationMs": 2312
    },
    {
      "ok": true,
      "skipped": false,
      "configured": true,
      "branch": "runtime-status",
      "path": "runtime/product-semantic-matrix.json",
      "attempts": 1,
      "durationMs": 2698
    },
    {
      "ok": true,
      "skipped": false,
      "configured": true,
      "branch": "runtime-status",
      "path": "runtime/tenant-channel-binding-matrix.json",
      "attempts": 1,
      "durationMs": 5999
    },
    {
      "ok": true,
      "skipped": false,
      "configured": true,
      "branch": "runtime-status",
      "path": "runtime/maximal-flow-matrix.json",
      "attempts": 1,
      "durationMs": 5991
    },
    {
      "ok": true,
      "skipped": false,
      "configured": true,
      "branch": "runtime-status",
      "path": "runtime/live-official-channel-resolution.json",
      "attempts": 1,
      "durationMs": 7800
    },
    {
      "ok": true,
      "skipped": false,
      "configured": true,
      "branch": "runtime-status",
      "path": "runtime/process-events.json",
      "attempts": 1,
      "durationMs": 2005
    },
    {
      "ok": true,
      "skipped": false,
      "configured": true,
      "branch": "runtime-status",
      "path": "runtime/northflank-startup-log.json",
      "attempts": 1,
      "durationMs": 1601
    },
    {
      "ok": true,
      "skipped": false,
      "configured": true,
      "branch": "runtime-status",
      "path": "runtime/live-tenant-self-diagnostic-matrix.json",
      "attempts": 1,
      "durationMs": 1504
    },
    {
      "ok": true,
      "skipped": false,
      "configured": true,
      "branch": "runtime-status",
      "path": "runtime/tenant-section-matrix.json",
      "attempts": 1,
      "durationMs": 3299
    },
    {
      "ok": true,
      "skipped": false,
      "configured": true,
      "branch": "runtime-status",
      "path": "runtime/live-user-postgres-bindings.json",
      "attempts": 1,
      "durationMs": 2793
    }
  ],
  "missingFiles": [],
  "summary": {
    "expectedCount": 12,
    "okCount": 12,
    "skippedCount": 0,
    "failedCount": 0,
    "missingCount": 0
  }
}
