{
  "runtime": "CC8.3.66-PR226-GROWTH-SOURCES-FUNNEL-STATS",
  "buttons": [
    "BTN-001",
    "BTN-002",
    "BTN-003",
    "BTN-004",
    "BTN-005",
    "BTN-006",
    "BTN-007",
    "BTN-008",
    "BTN-009",
    "BTN-010",
    "BTN-011",
    "BTN-012",
    "BTN-013",
    "BTN-014",
    "BTN-015",
    "BTN-016",
    "BTN-017",
    "BTN-018",
    "BTN-019",
    "BTN-020",
    "BTN-021",
    "BTN-022",
    "BTN-023",
    "BTN-024",
    "BTN-025",
    "BTN-026",
    "BTN-027",
    "BTN-028",
    "BTN-029",
    "BTN-030",
    "BTN-031",
    "BTN-032",
    "BTN-033",
    "BTN-034",
    "BTN-035",
    "BTN-036",
    "BTN-037",
    "BTN-038",
    "BTN-039",
    "BTN-040",
    "BTN-041",
    "BTN-042",
    "BTN-043",
    "BTN-044",
    "BTN-045",
    "BTN-046",
    "BTN-047",
    "BTN-048",
    "BTN-049",
    "BTN-050",
    "BTN-051",
    "BTN-052",
    "BTN-053",
    "BTN-054",
    "BTN-055",
    "BTN-056",
    "BTN-057",
    "BTN-058",
    "BTN-059",
    "BTN-060",
    "BTN-061",
    "BTN-062",
    "BTN-063",
    "BTN-064",
    "BTN-065",
    "BTN-066",
    "BTN-067"
  ],
  "gifts": [
    "GIFT-001",
    "GIFT-002",
    "GIFT-003",
    "GIFT-004",
    "GIFT-005",
    "GIFT-006",
    "GIFT-007",
    "GIFT-008",
    "GIFT-009",
    "GIFT-010",
    "GIFT-011",
    "GIFT-012",
    "GIFT-013",
    "GIFT-014",
    "GIFT-015",
    "GIFT-016",
    "GIFT-017",
    "GIFT-018",
    "GIFT-019",
    "GIFT-020",
    "GIFT-021",
    "GIFT-022",
    "GIFT-023",
    "GIFT-024",
    "GIFT-025",
    "GIFT-026",
    "GIFT-027",
    "GIFT-028",
    "GIFT-029",
    "GIFT-030",
    "GIFT-031",
    "GIFT-032",
    "GIFT-033",
    "GIFT-034",
    "GIFT-035",
    "GIFT-036",
    "GIFT-037",
    "GIFT-038"
  ],
  "giftsAudit": {
    "fullyCanonical": true,
    "auditOnly": false,
    "canonicalContext": "resolveGiftContext(ctx,payload)",
    "commitContract": "commitGiftFeatureState canonical write -> read-back -> verify -> MAX patch",
    "traceTests": [
      "GIFT-034",
      "GIFT-035",
      "GIFT-036"
    ],
    "antiResurrection": "delete tombstone blocks campaign_commentKey and migration_channel_post re-imports",
    "renderedPayloadProof": [
      "GIFT-037 rendered delete payload -> confirm -> canonical delete",
      "GIFT-038 rendered replace payload -> replacement flow -> canonical replace"
    ]
  },
  "buttonStates": {
    "BL": "legacy/imported/previously patched button state exists, but canonical buttonSet is empty",
    "BA": "action availability mismatch: UI rendered edit/delete, but the next handler sees zero buttons",
    "BR": "recovery required: post is resolved but current buttons cannot be loaded"
  },
  "statsAudit": {
    "fullyCanonical": true,
    "rootSections": 5,
    "duplicatedRootSections": false,
    "fakeMetricsBlocked": true,
    "messageStatCapabilityProbe": true,
    "persistentStatsEvents": true,
    "debugLogNotAnalyticsSource": true,
    "periodFiltering": true,
    "sourceFiltering": true,
    "trackingLinkUiCanonical": true,
    "manualCostUiCanonical": true,
    "postStatsRealHandler": true,
    "messageStatRealProbeOrUnavailable": true,
    "realEventProducers": true,
    "oldDuplicateActionsRerouted": true,
    "serviceShortcutTestsRejected": true
  }
}
